uniudpubapi/__init__.py
uniudpubapi/dep_pubs.py
uniudpubapi/elements.py
uniudpubapi/publications.py
uniudpubapi/writers.py
uniudpubapi/utils/__init__.py
uniudpubapi/utils/decorators.py
uniudpubapi/utils/oai_search.py
uniudpubapi-1.0.1.dist-info/LICENSE.txt
uniudpubapi-1.0.1.dist-info/METADATA
uniudpubapi-1.0.1.dist-info/WHEEL
uniudpubapi-1.0.1.dist-info/top_level.txt
uniudpubapi-1.0.1.dist-info/RECORD
