Metadata-Version: 2.1
Name: uniudpubapi
Version: 1.0.1
Summary: Package per l'importazione delle pubblicazioni dall'archivio istituzionale dell'Università degli studi di Udine
Home-page: https://github.com/Zinni98/publication-API
Author: Alessandro Zinni
Author-email: alessandro.zinni98@gmail.com
License: MIT
Project-URL: Source, https://github.com/Zinni98/publication-API
Keywords: publications,uniud,pubblicazioni
Platform: UNKNOWN
Classifier: Development Status :: 5 - Production/Stable
Classifier: Intended Audience :: Developers
Classifier: Topic :: Software Development :: Build Tools
Classifier: License :: OSI Approved :: MIT License
Classifier: Programming Language :: Python :: 3
Classifier: Programming Language :: Python :: 3.7
Classifier: Programming Language :: Python :: 3.8
Classifier: Programming Language :: Python :: 3.9
Classifier: Programming Language :: Python :: 3 :: Only
Requires-Python: >=3.7, <4
Requires-Dist: beautifulsoup4
Requires-Dist: lxml
Requires-Dist: bibtexparser
Requires-Dist: requests
